spinal_tap/__init__.py
spinal_tap/app.py
spinal_tap/callbacks.py
spinal_tap/layout.py
spinal_tap/utils.py
spinal_tap/version.py
spinal_tap/assets/base.css
spinal_tap/assets/favicon.ico
spinal_tap/assets/normalize.css
spinal_tap-0.3.0.dist-info/METADATA
spinal_tap-0.3.0.dist-info/WHEEL
spinal_tap-0.3.0.dist-info/entry_points.txt
spinal_tap-0.3.0.dist-info/top_level.txt
spinal_tap-0.3.0.dist-info/RECORD
