Metadata-Version: 2.4
Name: spinal-tap
Version: 0.3.0
Summary: SPINE Reconstruction Visualization Tool
Author-email: DeepLearnPhysics Collaboration <drielsma@stanford.edu>
Maintainer-email: Francois Drielsma <drielsma@stanford.edu>
Requires-Python: >=3.8
Requires-Dist: spine-ml[viz]>=0.9.3
Requires-Dist: dash>=3.0.0
Requires-Dist: flask>=2.0.0
Requires-Dist: flask-session>=0.5.0
Requires-Dist: anywidget
Provides-Extra: dev
Requires-Dist: black; extra == "dev"
Requires-Dist: isort; extra == "dev"
Requires-Dist: flake8; extra == "dev"
